gaia_beet/__init__.py
gaia_beet/api.py
gaia_beet/density_functions.py
gaia_beet/py.typed
gaia_beet-0.5.1.dist-info/LICENSE
gaia_beet-0.5.1.dist-info/WHEEL
gaia_beet-0.5.1.dist-info/METADATA
gaia_beet-0.5.1.dist-info/RECORD
