Metadata-Version: 2.1
Name: gaia-beet
Version: 0.5.1
Summary: Beet plugin to generate Minecraft worldgen files
Home-page: https://github.com/misode/gaia-beet
License: MIT
Keywords: beet,minecraft,gaia,worldgen
Author: Misode
Requires-Python: >=3.8,<4.0
Classifier: License :: OSI Approved :: MIT License
Classifier: Programming Language :: Python :: 3
Classifier: Programming Language :: Python :: 3.10
Classifier: Programming Language :: Python :: 3.8
Classifier: Programming Language :: Python :: 3.9
Requires-Dist: beet (>=0.45.3)
Project-URL: Repository, https://github.com/misode/gaia-beet
